flexhook/__init__.py
flexhook/exc.py
flexhook/hooks.py
flexhook/scope.py
flexhook-0.2.5.dist-info/LICENSE
flexhook-0.2.5.dist-info/METADATA
flexhook-0.2.5.dist-info/WHEEL
flexhook-0.2.5.dist-info/RECORD
