Metadata-Version: 2.1
Name: flexhook
Version: 0.2.5
Summary: a tiny and flexible hook framework
License: MIT
Author: JamzumSum
Author-email: zzzzss990315@gmail.com
Requires-Python: >=3.8,<4.0
Classifier: License :: OSI Approved :: MIT License
Classifier: Programming Language :: Python :: 3
Classifier: Programming Language :: Python :: 3.8
Classifier: Programming Language :: Python :: 3.9
Classifier: Programming Language :: Python :: 3.10
Classifier: Programming Language :: Python :: 3.11
Requires-Dist: exceptiongroup (>=1.1.1,<2.0.0) ; python_version < "3.11"
Requires-Dist: typing-extensions (>=4.5.0,<5.0.0) ; python_version < "3.11"
